{"_id":"debug-fabulous","_rev":"11-d9e8d8e201795b31d900aa1bcf933f65","name":"debug-fabulous","description":"visionmedia debug extensions rolled into one","dist-tags":{"latest":"1.0.0"},"versions":{"0.0.2":{"name":"debug-fabulous","version":"0.0.2","description":"visionmedia debug extensions rolled into one","main":"index.js","scripts":{"test":"mocha ./test/**/*test.js"},"repository":{"type":"git","url":"http://www.github.com/nmccready/debug-fabulous"},"keywords":["debug","lazy","lazy-eval"],"author":{"name":"Nicholas McCready"},"license":"MIT","dependencies":{"debug":"2.X","lazy-debug":"0.X","object-assign":"4.1.0"},"devDependencies":{"chai":"3.X","eslint":"3.X","mocha":"3.X"},"gitHead":"5f4ab5df6b263419646c5027f8babea76376e4dc","_id":"debug-fabulous@0.0.2","_shasum":"5e3bed8f3ebfdd4e2d9bfb87179bbf160a8df1a3","_from":".","_npmVersion":"2.15.11","_nodeVersion":"4.5.0","_npmUser":{"name":"nmccready","email":"nemtcan@gmail.com"},"maintainers":[{"name":"nmccready","email":"nemtcan@gmail.com"}],"dist":{"shasum":"5e3bed8f3ebfdd4e2d9bfb87179bbf160a8df1a3","tarball":"https://registry.npmjs.org/debug-fabulous/-/debug-fabulous-0.0.2.tgz"},"_npmOperationalInternal":{"host":"packages-16-east.internal.npmjs.com","tmp":"tmp/debug-fabulous-0.0.2.tgz_1476222160296_0.2146097864024341"},"directories":{}},"0.0.3":{"name":"debug-fabulous","version":"0.0.3","description":"visionmedia debug extensions rolled into one","main":"index.js","scripts":{"test":"mocha ./test/**/*test.js"},"repository":{"type":"git","url":"http://www.github.com/nmccready/debug-fabulous"},"keywords":["debug","lazy","lazy-eval"],"author":{"name":"Nicholas McCready"},"license":"MIT","dependencies":{"debug":"2.X","lazy-debug":"0.X","object-assign":"4.1.0"},"devDependencies":{"babel-eslint":"7.X","chai":"3.X","eslint":"3.X","hook-std":"0.X","mocha":"3.X"},"gitHead":"6cee36ae4a7916aba7a7724469555f365cacddd3","_id":"debug-fabulous@0.0.3","_shasum":"d154582976646bcf35b4b8a47ce174439dd5019b","_from":".","_npmVersion":"2.15.11","_nodeVersion":"4.5.0","_npmUser":{"name":"nmccready","email":"nemtcan@gmail.com"},"maintainers":[{"name":"nmccready","email":"nemtcan@gmail.com"}],"dist":{"shasum":"d154582976646bcf35b4b8a47ce174439dd5019b","tarball":"https://registry.npmjs.org/debug-fabulous/-/debug-fabulous-0.0.3.tgz"},"_npmOperationalInternal":{"host":"packages-16-east.internal.npmjs.com","tmp":"tmp/debug-fabulous-0.0.3.tgz_1476230894103_0.43484283913858235"},"directories":{}},"0.0.4":{"name":"debug-fabulous","version":"0.0.4","description":"visionmedia debug extensions rolled into one","main":"index.js","scripts":{"test":"mocha ./test/**/*test.js"},"repository":{"type":"git","url":"http://www.github.com/nmccready/debug-fabulous"},"keywords":["debug","lazy","lazy-eval"],"author":{"name":"Nicholas McCready"},"license":"MIT","dependencies":{"debug":"2.X","lazy-debug-legacy":"0.0.X","object-assign":"4.1.0"},"devDependencies":{"babel-eslint":"7.X","chai":"3.X","eslint":"3.X","hook-std":"0.X","mocha":"3.X"},"gitHead":"696f343617dce122ae03dc95e47050e48e87e3d4","_id":"debug-fabulous@0.0.4","_shasum":"fa071c5d87484685424807421ca4b16b0b1a0763","_from":".","_npmVersion":"2.15.1","_nodeVersion":"0.12.16","_npmUser":{"name":"nmccready","email":"nemtcan@gmail.com"},"maintainers":[{"name":"nmccready","email":"nemtcan@gmail.com"}],"dist":{"shasum":"fa071c5d87484685424807421ca4b16b0b1a0763","tarball":"https://registry.npmjs.org/debug-fabulous/-/debug-fabulous-0.0.4.tgz"},"_npmOperationalInternal":{"host":"packages-16-east.internal.npmjs.com","tmp":"tmp/debug-fabulous-0.0.4.tgz_1476277359814_0.7783828382380307"},"directories":{}},"0.1.0":{"name":"debug-fabulous","version":"0.1.0","description":"visionmedia debug extensions rolled into one","main":"index.js","scripts":{"mocha":"mocha $@","test":"mocha ./test/**/*test.js ./test/*.test.js"},"repository":{"type":"git","url":"http://www.github.com/nmccready/debug-fabulous"},"keywords":["debug","lazy","lazy-eval"],"author":{"name":"Nicholas McCready"},"license":"MIT","dependencies":{"debug":"2.X","object-assign":"4.1.0"},"devDependencies":{"babel-eslint":"7.X","chai":"3.X","eslint":"3.X","hook-std":"0.X","mocha":"3.X"},"gitHead":"c1d34dd89039823fb0ac4a0dac81672ff48b8cf1","_id":"debug-fabulous@0.1.0","_shasum":"ad0ea07a5d519324fb55842a8f34ee59c7f8ff6c","_from":".","_npmVersion":"4.4.4","_nodeVersion":"4.8.0","_npmUser":{"name":"nmccready","email":"nemtcan@gmail.com"},"dist":{"shasum":"ad0ea07a5d519324fb55842a8f34ee59c7f8ff6c","tarball":"https://registry.npmjs.org/debug-fabulous/-/debug-fabulous-0.1.0.tgz"},"maintainers":[{"name":"nmccready","email":"nemtcan@gmail.com"}],"_npmOperationalInternal":{"host":"packages-18-east.internal.npmjs.com","tmp":"tmp/debug-fabulous-0.1.0.tgz_1490974539088_0.04610411426983774"},"directories":{}},"0.1.1":{"name":"debug-fabulous","version":"0.1.1","description":"visionmedia debug extensions rolled into one","main":"index.js","scripts":{"lint":"eslint !./node_modules *.js ./**/*.js","mocha":"mocha","test":"npm run lint && mocha ./test/**/*test.js ./test/*.test.js"},"repository":{"type":"git","url":"http://www.github.com/nmccready/debug-fabulous"},"keywords":["debug","lazy","lazy-eval"],"author":{"name":"Nicholas McCready"},"license":"MIT","dependencies":{"debug":"2.3.0","memoizee":"^0.4.5","object-assign":"4.1.0"},"devDependencies":{"chai":"3.X","eslint":"3.X","hook-std":"0.X","memwatch-next":"^0.3.0","mocha":"3.X"},"gitHead":"bc8d55eac5ec12c37068213c10bd8bdf50ef2f60","_id":"debug-fabulous@0.1.1","_npmVersion":"5.0.4","_nodeVersion":"6.10.3","_npmUser":{"name":"nmccready","email":"nemtcan@gmail.com"},"dist":{"integrity":"sha512-UhD+fzBYnlHjOpUrSeKT+sbZAqxDsqoXAsESKQPAoBm2j/0F9l9IeOEYDST8Lkz1L2zA9KvIxp58h923wCWjDQ==","shasum":"1b970878c9fa4fbd1c88306eab323c830c58f1d6","tarball":"https://registry.npmjs.org/debug-fabulous/-/debug-fabulous-0.1.1.tgz"},"maintainers":[{"name":"nmccready","email":"nemtcan@gmail.com"}],"_npmOperationalInternal":{"host":"s3://npm-registry-packages","tmp":"tmp/debug-fabulous-0.1.1.tgz_1499904040166_0.25709694903343916"},"directories":{}},"0.1.2":{"name":"debug-fabulous","version":"0.1.2","description":"visionmedia debug extensions rolled into one","main":"index.js","scripts":{"lint":"eslint !./node_modules *.js ./**/*.js","mocha":"mocha","test":"npm run lint && mocha ./test/**/*test.js ./test/*.test.js"},"repository":{"type":"git","url":"http://www.github.com/nmccready/debug-fabulous"},"keywords":["debug","lazy","lazy-eval"],"author":{"name":"Nicholas McCready"},"license":"MIT","dependencies":{"debug":"^2.6.9","memoizee":"0.4.X","object-assign":"4.X"},"devDependencies":{"chai":"3.X","eslint":"3.X","hook-std":"0.X","memwatch-next":"0.3.X","mocha":"3.X"},"gitHead":"f2e6c96ce5fd6b2b642077d8c0285213d8491c5a","_id":"debug-fabulous@0.1.2","_npmVersion":"5.2.0","_nodeVersion":"6.10.3","_npmUser":{"name":"nmccready","email":"nemtcan@gmail.com"},"dist":{"integrity":"sha512-7f5cKUu19x1/E1piQCVeRSjJ/YW6se26OKr9GFVj7wOONqdCuhkAsKvgtJpq5gL8HSiMEuohM5hNwDN4SIOblg==","shasum":"c63ac4df92a13690b8b79d511401d653b0a31767","tarball":"https://registry.npmjs.org/debug-fabulous/-/debug-fabulous-0.1.2.tgz"},"maintainers":[{"name":"nmccready","email":"nemtcan@gmail.com"}],"_npmOperationalInternal":{"host":"s3://npm-registry-packages","tmp":"tmp/debug-fabulous-0.1.2.tgz_1506654786618_0.4175536159891635"},"directories":{}},"0.2.1":{"name":"debug-fabulous","version":"0.2.1","description":"visionmedia debug extensions rolled into one","main":"index.js","scripts":{"lint":"eslint !./node_modules *.js ./**/*.js","mocha":"mocha","test":"npm run lint && mocha ./test/**/*test.js ./test/*.test.js"},"repository":{"type":"git","url":"http://www.github.com/nmccready/debug-fabulous"},"keywords":["debug","lazy","lazy-eval"],"author":{"name":"Nicholas McCready"},"license":"MIT","dependencies":{"debug":"3.X","memoizee":"0.4.X","object-assign":"4.X"},"devDependencies":{"chai":"3.X","eslint":"3.X","hook-std":"0.X","memwatch-next":"0.3.X","mocha":"3.X"},"gitHead":"2da277367333fc9c19c2d2f79c6c0f6ba5cee366","_id":"debug-fabulous@0.2.1","_npmVersion":"5.2.0","_nodeVersion":"6.10.3","_npmUser":{"name":"nmccready","email":"nemtcan@gmail.com"},"dist":{"integrity":"sha512-u0TV6HcfLsZ03xLBhdhSViQMldaiQ2o+8/nSILaXkuNSWvxkx66vYJUAam0Eu7gAilJRX/69J4kKdqajQPaPyw==","shasum":"57e1164ba0e9ad6d9a65f20075ff3c2bd6bde0dc","tarball":"https://registry.npmjs.org/debug-fabulous/-/debug-fabulous-0.2.1.tgz"},"maintainers":[{"name":"nmccready","email":"nemtcan@gmail.com"}],"_npmOperationalInternal":{"host":"s3://npm-registry-packages","tmp":"tmp/debug-fabulous-0.2.1.tgz_1506655136446_0.6122905733063817"},"directories":{}},"1.0.0":{"name":"debug-fabulous","version":"1.0.0","description":"visionmedia debug extensions rolled into one","main":"index.js","scripts":{"lint":"eslint !./node_modules *.js ./**/*.js","mocha":"mocha","test":"npm run lint && mocha ./test/**/*test.js ./test/*.test.js"},"repository":{"type":"git","url":"http://www.github.com/nmccready/debug-fabulous"},"keywords":["debug","lazy","lazy-eval"],"author":{"name":"Nicholas McCready"},"license":"MIT","dependencies":{"debug":"3.X","memoizee":"0.4.X","object-assign":"4.X"},"devDependencies":{"JSONStream":"1.X","chai":"4.X","eslint":"4.X","hook-std":"0.X","memwatch-next":"0.3.X","mocha":"4.X"},"gitHead":"6c832633830fe8f03dafc5e1a90f4796cacddcf2","_id":"debug-fabulous@1.0.0","_npmVersion":"5.5.1","_nodeVersion":"8.9.3","_npmUser":{"name":"nmccready","email":"nemtcan@gmail.com"},"dist":{"integrity":"sha512-dsd50qQ1atDeurcxL7XOjPp4nZCGZzWIONDujDXzl1atSyC3hMbZD+v6440etw+Vt0Pr8ce4TQzHfX3KZM05Mw==","shasum":"57f6648646097b1b0849dcda0017362c1ec00f8b","tarball":"https://registry.npmjs.org/debug-fabulous/-/debug-fabulous-1.0.0.tgz"},"maintainers":[{"name":"nmccready","email":"nemtcan@gmail.com"}],"_npmOperationalInternal":{"host":"s3://npm-registry-packages","tmp":"tmp/debug-fabulous-1.0.0.tgz_1512886234869_0.10061591560952365"},"directories":{}}},"readme":"# debug-fabulous [![NPM version][npm-image]][npm-url] [![build status][travis-image]][travis-url]\n\n## Install\n\n`npm install --save debug-fabulous`\n\n## Purpose:\n\nWrapper / Extension around [visionmedia's debug](https://github.com/visionmedia/debug) to allow lazy evaluation of debugging via closure handling.\n\n## Why would I consider using this library?\n\nOne on the main utilities added to this library is lazy log level evaluation. This allows whatever log strings to only be created and evaluated if a log level is active. This can considerably reduce the amount of memory used in logging when you are not using.\n\nThis is important as this results in no-excuse for not using logging in your applications for performance reasons.\n\n### Proof\n\nFor analysis of the performance results are in [perfWith.out](./test/perf/perfWith.out) and [perfWithout.out](./test/perf/perfWithout.out).\n\nIn summary, the tests using this library are using 3 times less memory for the same logging statements (when the log levels are disabled).\n\n## This library essentially wraps two things:\n\n- [lazy-eval](./src/lazy-eval.js): debug closure handling\n- [spawn](./src/spawn.js): spawns off existing namespaces for a sub namespace.\n\n## Example:\n\nFor usage see the [tests](./test) or the example below.\n\n```js\nvar debug = require('')();\n// force namespace to be enabled otherwise it assumes process.env.DEBUG is setup\n// debug.save('namespace');\n// debug.enable(debug.load())\ndebug = debug('namespace'); // debugger in the namespace\ndebug(function(){return 'something to log' + someLargeHarryString;});\ndebug(() => 'something to log ${someLargeHarryString}');\ndebug('small out'); // prints namespace small out\nvar childDbg = debug.spawn('child'); // debugger in the namespace:child\nchildDbg('small out'); // prints namespace:child small out\nvar grandChildDbg = debug.spawn('grandChild'); // debugger in the namespace:child:grandChild\ngrandChildDbg('small out'); // prints namespace:child:grandChild small out\n```\n\n[npm-image]: https://img.shields.io/npm/v/debug-fabulous.svg\n[npm-url]: https://www.npmjs.com/package/debug-fabulous\n[travis-image]: https://img.shields.io/travis/nmccready/debug-fabulous.svg\n[travis-url]: https://travis-ci.org/nmccready/debug-fabulous\n","maintainers":[{"name":"nmccready","email":"nemtcan@gmail.com"}],"time":{"modified":"2017-12-22T15:59:37.330Z","created":"2016-10-11T21:38:20.194Z","0.0.1":"2016-10-11T21:38:20.194Z","0.0.2":"2016-10-11T21:42:40.959Z","0.0.3":"2016-10-12T00:08:14.805Z","0.0.4":"2016-10-12T13:02:40.559Z","0.1.0":"2017-03-31T15:35:39.781Z","0.1.1":"2017-07-13T00:00:41.058Z","0.1.2":"2017-09-29T03:13:07.524Z","0.2.1":"2017-09-29T03:18:57.349Z","1.0.0":"2017-12-10T06:10:35.848Z"},"keywords":["debug","lazy","lazy-eval"],"repository":{"type":"git","url":"http://www.github.com/nmccready/debug-fabulous"},"author":{"name":"Nicholas McCready"},"license":"MIT","readmeFilename":"README.md","users":{"nmccready":true},"_attachments":{},"_etag":"\"5a3d2be9-329a\"","_lastModified":"Fri, 22 Dec 2017 15:59:37 GMT","_cached":true}